huaweicloudsdkmas/__init__.py
huaweicloudsdkmas/v1/__init__.py
huaweicloudsdkmas/v1/mas_async_client.py
huaweicloudsdkmas/v1/mas_client.py
huaweicloudsdkmas/v1/model/__init__.py
huaweicloudsdkmas/v1/model/base_multi_active_zone_spec.py
huaweicloudsdkmas/v1/model/data_sync_statistics.py
huaweicloudsdkmas/v1/model/datasource_statistics.py
huaweicloudsdkmas/v1/model/multi_active_zone_vo.py
huaweicloudsdkmas/v1/model/namespace_vo.py
huaweicloudsdkmas/v1/model/show_name_space_list_request.py
huaweicloudsdkmas/v1/model/show_name_space_list_response.py
huaweicloudsdkmas/v1/region/__init__.py
huaweicloudsdkmas/v1/region/mas_region.py
huaweicloudsdkmas-3.1.184.dist-info/METADATA
huaweicloudsdkmas-3.1.184.dist-info/WHEEL
huaweicloudsdkmas-3.1.184.dist-info/licenses/LICENSE
huaweicloudsdkmas-3.1.184.dist-info/RECORD
